quetz/__init__.py
quetz/_version.py
quetz/authorization.py
quetz/channel_data.py
quetz/cli.py
quetz/condainfo.py
quetz/config.py
quetz/config.toml
quetz/dao.py
quetz/database.py
quetz/database_extensions.py
quetz/db_models.py
quetz/deps.py
quetz/errors.py
quetz/exceptions.py
quetz/frontend.py
quetz/hooks.py
quetz/main.py
quetz/pkgstores.py
quetz/repo_data.py
quetz/rest_models.py
quetz/utils.py
quetz/versionorder.py
quetz/authentication/__init__.py
quetz/authentication/auth_dao.py
quetz/authentication/azuread.py
quetz/authentication/base.py
quetz/authentication/github.py
quetz/authentication/gitlab.py
quetz/authentication/google.py
quetz/authentication/jupyterhub.py
quetz/authentication/oauth2.py
quetz/authentication/pam.py
quetz/authentication/registry.py
quetz/basic_frontend/avatar.jpg
quetz/basic_frontend/favicon.ico
quetz/basic_frontend/index.html
quetz/jobs/__init__.py
quetz/jobs/api.py
quetz/jobs/dao.py
quetz/jobs/handlers.py
quetz/jobs/models.py
quetz/jobs/rest_models.py
quetz/jobs/runner.py
quetz/metrics/__init__.py
quetz/metrics/api.py
quetz/metrics/db_models.py
quetz/metrics/middleware.py
quetz/metrics/rest_models.py
quetz/metrics/tasks.py
quetz/metrics/view.py
quetz/migrations/env.py
quetz/migrations/script.py.mako
quetz/migrations/versions/0653794b6252_adding_url_and_platforms_dirs.py
quetz/migrations/versions/0a0ab48887ab_adding_function_args_to_job_spec.py
quetz/migrations/versions/30241b33d849_add_task_pending_state.py
quetz/migrations/versions/303ff70c27fc_configure_mirror_endpoints.py
quetz/migrations/versions/3ba25f23fb7d_update_scoped_api_key_uploader_id.py
quetz/migrations/versions/3c3288034362_add_channel_metadata.py
quetz/migrations/versions/53f81aba78ce_use_biginteger_for_size.py
quetz/migrations/versions/794249a0b1bd_adding_jobs_tables.py
quetz/migrations/versions/8d1e9a9e0b1f_adding_download_metrics.py
quetz/migrations/versions/8dfb7c4bfbd7_new_package_versions.py
quetz/migrations/versions/98c04a65df4a_register_mirrors.py
quetz/tests/data/dummy-plugin/quetz_dummyplugin-1.0-py3.egg-info/entry_points.txt
quetz/tests/data/dummy-plugin/quetz_dummyplugin-1.0-py3.egg-info/top_level.txt
quetz_server-0.10.4.dist-info/LICENSE
quetz_server-0.10.4.dist-info/METADATA
quetz_server-0.10.4.dist-info/WHEEL
quetz_server-0.10.4.dist-info/entry_points.txt
quetz_server-0.10.4.dist-info/top_level.txt
quetz_server-0.10.4.dist-info/RECORD
