Metadata-Version: 2.1
Name: quetz-server
Version: 0.10.4
Summary: The mamba-org server for conda packages
Home-page: https://github.com/mamba-org/quetz
Author: QuantStack & Quetz contributors
Author-email: wolf.vollprecht@quantstack.net
Keywords: conda,mamba,server
Platform: Linux
Platform: Mac OS X
Requires-Python: >=3.7
License-File: LICENSE
Requires-Dist: alembic
Requires-Dist: aiofiles
Requires-Dist: appdirs
Requires-Dist: authlib <1.0.0
Requires-Dist: fastapi
Requires-Dist: fsspec
Requires-Dist: h2
Requires-Dist: httpx >=0.22.0
Requires-Dist: importlib-metadata
Requires-Dist: itsdangerous
Requires-Dist: jinja2
Requires-Dist: pluggy
Requires-Dist: prometheus-client
Requires-Dist: python-multipart
Requires-Dist: pydantic >=2.0.0
Requires-Dist: pyyaml
Requires-Dist: requests
Requires-Dist: sqlalchemy
Requires-Dist: sqlalchemy-utils
Requires-Dist: tenacity
Requires-Dist: toml
Requires-Dist: typer <1.0,>=0.9
Requires-Dist: typing-extensions
Requires-Dist: ujson
Requires-Dist: uvicorn
Requires-Dist: zstandard
Requires-Dist: aioshutil
Provides-Extra: all
Requires-Dist: adlfs ; extra == 'all'
Requires-Dist: gcsfs >=2022.02 ; extra == 'all'
Requires-Dist: pamela ; extra == 'all'
Requires-Dist: psycopg2 ; extra == 'all'
Requires-Dist: s3fs ; extra == 'all'
Provides-Extra: azure
Requires-Dist: adlfs ; extra == 'azure'
Provides-Extra: client
Requires-Dist: quetz-client ; extra == 'client'
Provides-Extra: dev
Requires-Dist: black ; extra == 'dev'
Requires-Dist: flake8 ; extra == 'dev'
Requires-Dist: isort ; extra == 'dev'
Requires-Dist: pre-commit ; extra == 'dev'
Requires-Dist: pytest ; extra == 'dev'
Requires-Dist: pytest-asyncio ; extra == 'dev'
Requires-Dist: pytest-mock ; extra == 'dev'
Requires-Dist: pytest-cov ; extra == 'dev'
Requires-Dist: pytest-timeout ; extra == 'dev'
Requires-Dist: tbump ; extra == 'dev'
Provides-Extra: gcs
Requires-Dist: gcsfs >=2022.02 ; extra == 'gcs'
Provides-Extra: pam
Requires-Dist: pamela ; extra == 'pam'
Provides-Extra: postgre
Requires-Dist: psycopg2 ; extra == 'postgre'
Provides-Extra: s3
Requires-Dist: s3fs ; extra == 's3'
Provides-Extra: test
Requires-Dist: black ; extra == 'test'
Requires-Dist: flake8 ; extra == 'test'
Requires-Dist: isort ; extra == 'test'
Requires-Dist: pre-commit ; extra == 'test'
Requires-Dist: pytest ; extra == 'test'
Requires-Dist: pytest-asyncio ; extra == 'test'
Requires-Dist: pytest-mock ; extra == 'test'
Requires-Dist: pytest-cov ; extra == 'test'
Requires-Dist: pytest-timeout ; extra == 'test'
Requires-Dist: tbump ; extra == 'test'
